mem_usage_ui/__init__.py
mem_usage_ui/__main__.py
mem_usage_ui/routes.py
mem_usage_ui/settings.py
mem_usage_ui/snapshot.py
mem_usage_ui/static/img/android-chrome-192x192.png
mem_usage_ui/static/img/android-chrome-512x512.png
mem_usage_ui/static/img/apple-touch-icon.png
mem_usage_ui/static/img/favicon-16x16.png
mem_usage_ui/static/img/favicon-32x32.png
mem_usage_ui/static/img/favicon.ico
mem_usage_ui/static/img/site.webmanifest
mem_usage_ui/static/js/build.js
mem_usage_ui/static/js/build.js.LICENSE.txt
mem_usage_ui/static/js/build.js.map
mem_usage_ui/templates/index.html
mem_usage_ui/tests/__init__.py
mem_usage_ui/tests/test_views.py
mem_usage_ui/views.py
mem_usage_ui-1.0.9.dist-info/LICENSE
mem_usage_ui-1.0.9.dist-info/METADATA
mem_usage_ui-1.0.9.dist-info/WHEEL
mem_usage_ui-1.0.9.dist-info/entry_points.txt
mem_usage_ui-1.0.9.dist-info/RECORD
