Metadata-Version: 2.1
Name: mem-usage-ui
Version: 1.0.9
Summary: Measuring and graphing memory usage of local processes
License: MIT
Author: Dmytro Smyk
Author-email: porovozls@gmail.com
Requires-Python: >=3.7,<4
Classifier: License :: OSI Approved :: MIT License
Classifier: Programming Language :: Python :: 3
Classifier: Programming Language :: Python :: 3.7
Classifier: Programming Language :: Python :: 3.8
Classifier: Programming Language :: Python :: 3.9
Classifier: Programming Language :: Python :: 3.10
Classifier: Programming Language :: Python :: 3.11
Requires-Dist: aiohttp (>=3,<5)
Requires-Dist: psutil (<6)
